robotframework_propertyfile/__init__.py
robotframework_propertyfile/loader.py
RobotFramework_PropertyFile-0.0.1.dist-info/LICENSE
RobotFramework_PropertyFile-0.0.1.dist-info/METADATA
RobotFramework_PropertyFile-0.0.1.dist-info/WHEEL
RobotFramework_PropertyFile-0.0.1.dist-info/top_level.txt
RobotFramework_PropertyFile-0.0.1.dist-info/RECORD
