Metadata-Version: 2.1
Name: RobotFramework-PropertyFile
Version: 0.0.1
Summary: An utility package for exposing Java-style properties from property-files as variables in Robot Framework
Home-page: https://github.com/AdamHepner/robotframework-propertyfile
Author: Adam Hepner
Author-email: adam@hepner.eu
License: MIT
Platform: UNKNOWN
Classifier: License :: OSI Approved :: MIT License
Classifier: Programming Language :: Python :: 3
Classifier: Programming Language :: Python :: 3.7
Requires-Dist: jproperties
Requires-Dist: robotframework
